MANIFEST.in
Makefile
README
setup.cfg
setup.py
simplewiki
test/__init__.py
test/__init__.pyc
test/test_compile.py
test/__pycache__/test_compile.cpython-27-PYTEST.pyc
tiddlywebplugins/__init__.py
tiddlywebplugins.simplewiki.egg-info/PKG-INFO
tiddlywebplugins.simplewiki.egg-info/SOURCES.txt
tiddlywebplugins.simplewiki.egg-info/dependency_links.txt
tiddlywebplugins.simplewiki.egg-info/namespace_packages.txt
tiddlywebplugins.simplewiki.egg-info/not-zip-safe
tiddlywebplugins.simplewiki.egg-info/requires.txt
tiddlywebplugins.simplewiki.egg-info/top_level.txt
tiddlywebplugins/simplewiki/__init__.py
tiddlywebplugins/simplewiki/instance.py
tiddlywebplugins/simplewiki/resources/tiddlers.index
tiddlywebplugins/simplewiki/resources/wiki/FrontPage.tid
tiddlywebplugins/templates/changes.html
tiddlywebplugins/templates/css.html
tiddlywebplugins/templates/editor.html
tiddlywebplugins/templates/page.html
tiddlywebplugins/templates/simplewikibase.html