Metadata-Version: 1.0
Name: tiddlywebplugins.simplewiki
Version: 1.0.3
Summary: A simple markdown based wiki in TiddlyWeb
Home-page: http://pypi.python.org/pypi/tiddlywebplugins.simplewiki
Author: Chris Dent
Author-email: cdent@peermore.com
License: UNKNOWN
Platform: Posix; MacOS X; Windows
